volterra/__init__.py
volterra-0.0.1.dist-info/LICENSE
volterra-0.0.1.dist-info/METADATA
volterra-0.0.1.dist-info/WHEEL
volterra-0.0.1.dist-info/entry_points.txt
volterra-0.0.1.dist-info/top_level.txt
volterra-0.0.1.dist-info/RECORD
